pywyse/__init__.py
pywyse/basemodel.py
pywyse/client.py
pywyse/exceptions.py
pywyse/utils.py
pywyse/accounting/__init__.py
pywyse/accounting/expense.py
pywyse/accounting/invoice.py
pywyse/accounting/procurement.py
pywyse/agreement/__init__.py
pywyse/agreement/agreement.py
pywyse/company/__init__.py
pywyse/company/company.py
pywyse/expense/__init__.py
pywyse/expense/expense.py
pywyse/finance/__init__.py
pywyse/finance/finance.py
pywyse/invoicing/__init__.py
pywyse/invoicing/invoicing.py
pywyse/invoicing/models.py
pywyse/procurement/__init__.py
pywyse/procurement/models.py
pywyse/procurement/procurement.py
pywyse/project/__init__.py
pywyse/project/project.py
pywyse/sales/__init__.py
pywyse/sales/sales.py
pywyse/sell/__init__.py
pywyse/sell/sell.py
pywyse/service/__init__.py
pywyse/service/models.py
pywyse/service/service.py
pywyse/system/__init__.py
pywyse/system/system.py
pywyse/time/__init__.py
pywyse/time/models.py
pywyse/time/time.py
tests/__init__.py
tests/test_package.py
tests/test_utils.py
tests/accounting/__init__.py
tests/accounting/test_accounting.py
tests/company/__init__.py
tests/company/test_company.py
tests/invoicing/__init__.py
tests/invoicing/test_invoicing.py
tests/procurement/__init__.py
tests/procurement/test_procurement.py
tests/sales/__init__.py
tests/sales/test_sales.py
tests/sell/__init__.py
tests/sell/test_sell.py
tests/service/__init__.py
tests/service/test_tickets.py
tests/system/__init__.py
tests/system/test_system.py
pywyse-0.0.1.dist-info/METADATA
pywyse-0.0.1.dist-info/WHEEL
pywyse-0.0.1.dist-info/top_level.txt
pywyse-0.0.1.dist-info/RECORD
