Metadata-Version: 2.1
Name: pywyse
Version: 0.0.1
Summary: API client for ConnectWise Manage
Home-page: https://github.com/bill-ash/pywyse
Author: Bill Ash
Author-email: bill@overco.net
License: UNKNOWN
Project-URL: Bug Tracker, https://github.com/bill-ash/pywyse/issues
Platform: UNKNOWN
Classifier: Programming Language :: Python :: 3
Classifier: License :: OSI Approved :: MIT License
Classifier: Operating System :: OS Independent
Requires-Python: >=3.6
Requires-Dist: requests
Provides-Extra: tests
Requires-Dist: pytest ; extra == 'tests'
